pyojure/__init__.py
pyojure/core.py
pyojure-0.2.1.dist-info/LICENSE
pyojure-0.2.1.dist-info/METADATA
pyojure-0.2.1.dist-info/WHEEL
pyojure-0.2.1.dist-info/top_level.txt
pyojure-0.2.1.dist-info/RECORD
