Metadata-Version: 2.2
Name: pyojure
Version: 0.2.1
Summary: Make Python More Like Clojure
License-File: LICENSE
